server_monitor_agent/__init__.py
server_monitor_agent/entry.py
server_monitor_agent/agent/__init__.py
server_monitor_agent/agent/cli.py
server_monitor_agent/agent/command.py
server_monitor_agent/agent/common.py
server_monitor_agent/agent/consul.py
server_monitor_agent/agent/convert.py
server_monitor_agent/agent/instance.py
server_monitor_agent/agent/io.py
server_monitor_agent/agent/model.py
server_monitor_agent/agent/monitor.py
server_monitor_agent/agent/operation.py
server_monitor_agent/agent/registry.py
server_monitor_agent/agent/service.py
server_monitor_agent/agent/slack.py
server_monitor_agent/service/__init__.py
server_monitor_agent/service/alert_manager/__init__.py
server_monitor_agent/service/alert_manager/io.py
server_monitor_agent/service/alert_manager/model.py
server_monitor_agent/service/alert_manager/operation.py
server_monitor_agent/service/alert_manager/send.py
server_monitor_agent/service/consul/__init__.py
server_monitor_agent/service/consul/collect.py
server_monitor_agent/service/consul/io.py
server_monitor_agent/service/consul/model.py
server_monitor_agent/service/consul/operation.py
server_monitor_agent/service/disk/__init__.py
server_monitor_agent/service/disk/collect.py
server_monitor_agent/service/disk/io.py
server_monitor_agent/service/disk/model.py
server_monitor_agent/service/disk/operation.py
server_monitor_agent/service/disk/send.py
server_monitor_agent/service/docker/__init__.py
server_monitor_agent/service/docker/collect.py
server_monitor_agent/service/docker/io.py
server_monitor_agent/service/docker/model.py
server_monitor_agent/service/docker/operation.py
server_monitor_agent/service/server/__init__.py
server_monitor_agent/service/server/collect.py
server_monitor_agent/service/server/io.py
server_monitor_agent/service/server/model.py
server_monitor_agent/service/server/operation.py
server_monitor_agent/service/server/send.py
server_monitor_agent/service/statuscake/__init__.py
server_monitor_agent/service/statuscake/collect.py
server_monitor_agent-0.5.0.dist-info/LICENSE
server_monitor_agent-0.5.0.dist-info/METADATA
server_monitor_agent-0.5.0.dist-info/WHEEL
server_monitor_agent-0.5.0.dist-info/entry_points.txt
server_monitor_agent-0.5.0.dist-info/top_level.txt
server_monitor_agent-0.5.0.dist-info/RECORD
